agenthelm/__init__.py
agenthelm/agent/__init__.py
agenthelm/agent/base.py
agenthelm/agent/plan.py
agenthelm/agent/planner.py
agenthelm/agent/result.py
agenthelm/agent/tool_agent.py
agenthelm/cli/__init__.py
agenthelm/cli/config.py
agenthelm/cli/main.py
agenthelm/core/__init__.py
agenthelm/core/cost.py
agenthelm/core/event.py
agenthelm/core/handlers.py
agenthelm/core/tool.py
agenthelm/core/tracer.py
agenthelm/core/storage/__init__.py
agenthelm/core/storage/base.py
agenthelm/core/storage/json_storage.py
agenthelm/core/storage/sqlite_storage.py
agenthelm/mcp/__init__.py
agenthelm/mcp/adapter.py
agenthelm/mcp/client.py
agenthelm/memory/__init__.py
agenthelm/memory/base.py
agenthelm/memory/context.py
agenthelm/memory/hub.py
agenthelm/memory/semantic.py
agenthelm/memory/short_term/__init__.py
agenthelm/memory/short_term/in_memory.py
agenthelm/memory/short_term/redis.py
agenthelm/memory/short_term/sqlite.py
agenthelm/orchestration/__init__.py
agenthelm/orchestration/orchestrator.py
agenthelm/orchestration/registry.py
agenthelm/tracing/__init__.py
agenthelm/tracing/otel.py
agenthelm-0.3.0.dist-info/licenses/LICENSE
agenthelm-0.3.0.dist-info/METADATA
agenthelm-0.3.0.dist-info/WHEEL
agenthelm-0.3.0.dist-info/entry_points.txt
agenthelm-0.3.0.dist-info/top_level.txt
agenthelm-0.3.0.dist-info/RECORD
