Metadata-Version: 2.4
Name: agenthelm
Version: 0.3.0
Summary: A production-ready, observable, and reliable AI agent orchestration framework.
Requires-Python: >=3.12
License-File: LICENSE
Requires-Dist: dspy-ai>=2.5
Requires-Dist: pydantic>=2.0
Requires-Dist: redis>=5.0
Requires-Dist: qdrant-client>=1.12
Requires-Dist: sqlalchemy>=2.0
Requires-Dist: opentelemetry-api>=1.20
Requires-Dist: opentelemetry-sdk>=1.20
Requires-Dist: opentelemetry-exporter-otlp>=1.20
Requires-Dist: click>=8.0
Requires-Dist: rich>=13.0
Requires-Dist: pyyaml>=6.0
Requires-Dist: requests>=2.32
Requires-Dist: mcp>=1.25.0
Requires-Dist: python-dotenv>=1.2.1
Provides-Extra: dev
Requires-Dist: ruff>=0.5.5; extra == "dev"
Requires-Dist: pytest>=8.3.2; extra == "dev"
Requires-Dist: pytest-asyncio>=1.0; extra == "dev"
Requires-Dist: mkdocs>=1.6.0; extra == "dev"
Requires-Dist: mkdocs-material>=9.5.0; extra == "dev"
Requires-Dist: mkdocstrings[python]>=0.25.1; extra == "dev"
Requires-Dist: mike>=2.0; extra == "dev"
Requires-Dist: ty>=0.0.1a24; extra == "dev"
Requires-Dist: matplotlib>=3.10.7; extra == "dev"
Requires-Dist: networkx>=3.5; extra == "dev"
Dynamic: license-file
